planet_sim/__init__.py
planet_sim/planet_sim.py
planet_simulator-0.1.2.dist-info/licenses/LICENSE
planet_simulator-0.1.2.dist-info/METADATA
planet_simulator-0.1.2.dist-info/WHEEL
planet_simulator-0.1.2.dist-info/top_level.txt
planet_simulator-0.1.2.dist-info/RECORD
